[
  {
    "id": 0,
    "league": "Premier League",
    "team": "Liverpool",
    "fname": "Mohammed",
    "sname": "Salah",
    "overall": 9,
    "portrait": "img/Cards/Salah.png"
  },
  {
    "id": 1,
    "league": "Bundesliga",
    "team": "Dortmund",
    "fname": "Jaden",
    "sname": "Sancho",
    "overall": 7,
    "portrait": "img/Cards/Sancho.png"
  },
  {
    "id": 2,
    "league": "La Liga",
    "team": "Real Madrid",
    "fname": "Eden",
    "sname": "Hazard",
    "overall": 8,
    "portrait": "img/Cards/EHazard.png"
  },
  {
    "id": 3,
    "league": "Ligue 1",
    "team": "PSG",
    "fname": "Kylian",
    "sname": "Mbappe",
    "overall": 7,
    "portrait": "img/Cards/Mbappe.png"
  },
  {
    "id": 4,
    "league": "La Liga",
    "team": "Barcelona",
    "fname": "Lionel",
    "sname": "Messi",
    "overall": 10,
    "portrait": "img/Cards/Messi.png"
  },
  {
    "id": 5,
    "league": "Premier League",
    "team": "Spurs",
    "fname": "Harry",
    "sname": "Kane",
    "overall": 7,
    "portrait": "img/Cards/Kane.png"
  },
  {
    "id": 6,
    "league": "Premier League",
    "team": "Man City",
    "fname": "Raheem",
    "sname": "Sterling",
    "overall": 8,
    "portrait": "img/Cards/Sterling.png"
  },
  {
    "id": 7,
    "league": "Premier League",
    "team": "Arsenal",
    "fname": "Pierre-Emerick",
    "sname": "Aubameyang",
    "overall": 6,
    "portrait": "img/Cards/Aubameyang.png"
  },
  {
    "id": 8,
    "league": "Premier League",
    "team": "Man United",
    "fname": "Marcus",
    "sname": "Rashford",
    "overall": 6,
    "portrait": "img/Cards/Rashford.png"
  },
  {
    "id": 9,
    "league": "Premier League",
    "team": "Chelsea",
    "fname": "Christian",
    "sname": "Pulisic",
    "overall": 5,
    "portrait": "img/Cards/Pulisic.png"
  },
  {
    "id": 10,
    "league": "La Liga",
    "team": "Barcelona",
    "fname": "Luis",
    "sname": "Suarez",
    "overall": 7,
    "portrait": "img/Cards/Suarez.png"
  },
  {
    "id": 11,
    "league": "Serie A",
    "team": "Juventus",
    "fname": "Cristiano",
    "sname": "Ronaldo",
    "overall": 10,
    "portrait": "img/Cards/Ronaldo.png"
  },
  {
    "id": 12,
    "league": "Premier League",
    "team": "Man City",
    "fname": "Sergio",
    "sname": "Aguero",
    "overall": 9,
    "portrait": "img/Cards/Aguero.png"
  },
  {
    "id": 13,
    "league": "Premier League",
    "team": "Liverpool",
    "fname": "Virgil",
    "sname": "Van Dijk",
    "overall": 10,
    "portrait": "img/Cards/VVD.png"
  },
  {
    "id": 14,
    "league": "La Liga",
    "team": "Real Madrid",
    "fname": "Sergio",
    "sname": "Ramos",
    "overall": 8,
    "portrait": "img/Cards/Ramos.png"
  },
  {
    "id": 15,
    "league": "Bundesliga",
    "team": "Bayern Munich",
    "fname": "Manuel",
    "sname": "Neuer",
    "overall": 6,
    "portrait": "img/Cards/Neuer.png"
  },
  {
    "id": 16,
    "league": "Premier League",
    "team": "Man City",
    "fname": "Leroy",
    "sname": "Sane",
    "overall": 6,
    "portrait": "img/Cards/Sane.png"
  },
  {
    "id": 17,
    "league": "Premier League",
    "team": "Man City",
    "fname": "Kevin",
    "sname": "De Bruyne",
    "overall": 9,
    "portrait": "img/Cards/KDB.png"
  },
  {
    "id": 18,
    "league": "Premier League",
    "team": "Man City",
    "fname": "David",
    "sname": "Silva",
    "overall": 6,
    "portrait": "img/Cards/Silva.png"
  },
  {
    "id": 19,
    "league": "Premier League",
    "team": "Chelsea",
    "fname": "César",
    "sname": "Azpilicueta",
    "overall": 5,
    "portrait": "img/Cards/Azpi.png"
  },
  {
    "id": 20,
    "league": "Premier League",
    "team": "Spurs",
    "fname": "Harry",
    "sname": "Winks",
    "overall": 4,
    "portrait": "img/Cards/Winks.png"
  },
  {
    "id": 21,
    "league": "Premier League",
    "team": "Arsenal",
    "fname": "Alexandre",
    "sname": "Lacazette",
    "overall": 6,
    "portrait": "img/Cards/Lacazette.png"
  },

  {
    "id": 22,
    "league": "Premier League",
    "team": "Wolves",
    "fname": "Diego",
    "sname": "Jota",
    "overall": 5,
    "portrait": "img/Cards/Jota.png"
  },
  {
    "id": 23,
    "league": "La Liga",
    "team": "Barcelona",
    "fname": "Frankie",
    "sname": "De Jong",
    "overall": 7,
    "portrait": "img/Cards/FDeJong.png"
  },
  {
    "id": 24,
    "league": "La Liga",
    "team": "Real Madrid",
    "fname": "Raphael",
    "sname": "Varane",
    "overall": 7,
    "portrait": "img/Cards/Varane.png"
  },
  {
    "id": 25,
    "league": "La Liga",
    "team": "Atletico Madrid",
    "fname": "Jorge",
    "sname": "Koke",
    "overall": 6,
    "portrait": "img/Cards/Koke.png"
  },
  {
    "id": 26,
    "league": "Premier League",
    "team": "Bayern Munich",
    "fname": "Serge",
    "sname": "Gnabry",
    "overall": 7,
    "portrait": "img/Cards/Gnabry.png"
  },
  {
    "id": 27,
    "league": "Ligue 1",
    "team": "PSG",
    "fname": "Angel",
    "sname": "Di Maria",
    "overall": 8,
    "portrait": "img/Cards/DiMaria.png"
  },
  {
    "id": 28,
    "league": "Serie A",
    "team": "Inter Milan",
    "fname": "Radja",
    "sname": "Nainggolan",
    "overall": 5,
    "portrait": "img/Cards/Nainggolan.png"
  },
  {
    "id": 29,
    "league": "Premier League",
    "team": "Arsenal",
    "fname": "David",
    "sname": "Luiz",
    "overall": 4,
    "portrait": "img/Cards/Luiz.png"
  },
  {
    "id": 30,
    "league": "Premier League",
    "team": "Arsenal",
    "fname": "Hector",
    "sname": "Bellerin",
    "overall": 6,
    "portrait": "img/Cards/Bellerin.png"
  },
  {
    "id": 31,
    "league": "La Liga",
    "team": "Barcelona",
    "fname": "Jordi",
    "sname": "Alba",
    "overall": 7,
    "portrait": "img/Cards/Alba.png"
  },
  {
    "id": 32,
    "league": "Ligue 1",
    "team": "PSG",
    "fname": "Thiago",
    "sname": "Silva",
    "overall": 5,
    "portrait": "img/Cards/TSilva.png"
  },
  {
    "id": 33,
    "league": "La Liga",
    "team": "Barcelona",
    "fname": "Gerard",
    "sname": "Pique",
    "overall": 5,
    "portrait": "img/Cards/Pique.png"
  },
  {
    "id": 34,
    "league": "Serie A",
    "team": "Inter Milan",
    "fname": "Samir",
    "sname": "Handanovic",
    "overall": 7,
    "portrait": "img/Cards/Handanovic.png"
  },
  {
    "id": 35,
    "league": "Premier League",
    "team": "Man United",
    "fname": "David",
    "sname": "De Gea",
    "overall": 8,
    "portrait": "img/Cards/DDG.png"
  },
  {
    "id": 36,
    "league": "La Liga",
    "team": "Inter Milan",
    "fname": "Jan",
    "sname": "Oblak",
    "overall": 9,
    "portrait": "img/Cards/Oblak.png"
  },
  {
    "id": 37,
    "league": "La Liga",
    "team": "Barcelona",
    "fname": "Marc-Andre",
    "sname": "Ter Stegan",
    "overall": 8,
    "portrait": "img/Cards/TStegen.png"
  },
  {
    "id": 38,
    "league": "Premier League",
    "team": "Arsenal",
    "fname": "Bernd",
    "sname": "Leno",
    "overall": 7,
    "portrait": "img/Cards/Leno.png"
  },
  {
    "id": 39,
    "league": "Premier League",
    "team": "Chelsea",
    "fname": "Ngolo",
    "sname": "Kante",
    "overall": 8,
    "portrait": "img/Cards/Kante.png"
  }
]